[
    {
        "id": 10,
        "name": "App10",
        "icon": "../../assets/img/util.jpeg"
    },
    {
        "id": 20,
        "name": "App20",
        "icon": "../../assets/img/util.jpeg"
    },
    {
        "id": 30,
        "name": "App30",
        "icon": "../../assets/img/util.jpeg"
    },
    {
        "id": 40,
        "name": "App40",
        "icon": "../../assets/img/util.jpeg"
    },
    {
        "id": 50,
        "name": "App50",
        "icon": "../../assets/img/util.jpeg"
    },
    {
        "id": 60,
        "name": "App60",
        "icon": "../../assets/img/util.jpeg"
    },
    {
        "id": 70,
        "name": "App70",
        "icon": "../../assets/img/util.jpeg"
    },
    {
        "id": 80,
        "name": "App80",
        "icon": "../../assets/img/util.jpeg"
    },
    {
        "id": 90,
        "name": "App90",
        "icon": "../../assets/img/util.jpeg"
    },
    {
        "id": 100,
        "name": "App100",
        "icon": "../../assets/img/util.jpeg"
    }
]